hookman/__init__.py
hookman/__main__.py
hookman/exceptions.py
hookman/hookman_generator.py
hookman/hookman_utils.py
hookman/hooks.py
hookman/plugin_config.py
python_hookman-0.8.0.dist-info/licenses/AUTHORS.rst
python_hookman-0.8.0.dist-info/licenses/LICENSE
python_hookman-0.8.0.dist-info/METADATA
python_hookman-0.8.0.dist-info/WHEEL
python_hookman-0.8.0.dist-info/entry_points.txt
python_hookman-0.8.0.dist-info/top_level.txt
python_hookman-0.8.0.dist-info/RECORD
