Metadata-Version: 2.4
Name: python-hookman
Version: 0.8.0
Summary: HookMan is a python package that provides a plugin management system to applications, specially those who are written (in totally or partially) in C++.
Home-page: https://github.com/esss/hookman
Author: ESSS
Author-email: foss@esss.co
License: MIT license
Keywords: hookman
Classifier: Development Status :: 3 - Alpha
Classifier: Intended Audience :: Developers
Classifier: License :: OSI Approved :: MIT License
Classifier: Natural Language :: English
Classifier: Programming Language :: Python :: 3.10
Classifier: Programming Language :: Python :: 3.11
Classifier: Programming Language :: Python :: 3.12
Requires-Python: >=3.10
License-File: LICENSE
License-File: AUTHORS.rst
Requires-Dist: Click>=7.0
Requires-Dist: strictyaml
Requires-Dist: invoke
Requires-Dist: attrs
Provides-Extra: docs
Requires-Dist: sphinx>=1.4; extra == "docs"
Requires-Dist: sphinx_rtd_theme; extra == "docs"
Requires-Dist: sphinx-autodoc-typehints; extra == "docs"
Dynamic: author
Dynamic: author-email
Dynamic: classifier
Dynamic: description
Dynamic: description-content-type
Dynamic: home-page
Dynamic: keywords
Dynamic: license
Dynamic: license-file
Dynamic: provides-extra
Dynamic: requires-dist
Dynamic: requires-python
Dynamic: summary
